button/Btn.py
button/EsBtn.py
button/FillBtn.py
button/__init__.py
button/__main__.py
enter/Ent.py
enter/EsEnt.py
enter/FillEnt.py
enter/__init__.py
enter/__main__.py
image/ButtonImg.py
image/FillButtonImg.py
image/FillImg.py
image/Img.py
image/__init__.py
image/__main__.py
message/EsMsg.py
message/FillMsg.py
message/Msg.py
message/__init__.py
message/__main__.py
supermarket/__init__.py
supermarket/__main__.py
supermarket/imgbooks/Imgbook.py
supermarket/imgbooks/__init__.py
supermarket/imgbooks/__main__.py
supermarket/one_pagebook/OnePagebook.py
supermarket/one_pagebook/__init__.py
supermarket/one_pagebook/__main__.py
supermarket/pagebooks/Pagebook.py
supermarket/pagebooks/__init__.py
supermarket/pagebooks/__main__.py
supermarket/tools/Checker.py
supermarket/tools/__init__.py
supermarket/tools/__main__.py
supermarket/tools/SpecialButtons/FillButton.py
supermarket/tools/SpecialButtons/FillImgButton.py
supermarket/tools/SpecialButtons/__init__.py
supermarket/tools/SpecialButtons/__main__.py
tools/EasyDialog.py
tools/FillButton.py
tools/Manner.py
tools/__init__.py
tools/__main__.py
tools/colors.py
tools/SpecialButtons/ImgButton.py
tools/SpecialButtons/ImgFillButton.py
tools/SpecialButtons/__init__.py
tools/SpecialButtons/__main__.py
easyapp_don-0.2.3.dist-info/LICENSE.md
easyapp_don-0.2.3.dist-info/METADATA
easyapp_don-0.2.3.dist-info/WHEEL
easyapp_don-0.2.3.dist-info/top_level.txt
easyapp_don-0.2.3.dist-info/RECORD
