Metadata-Version: 2.1
Name: easyapp-don
Version: 0.2.3
Summary: A simple tool for building apps—even easier than Kivy and KivyMD!
Author: LvYanHua
Author-email: at034000@qq.com
License: MIT
Classifier: License :: OSI Approved :: MIT License
Requires-Python: >=3.7
License-File: LICENSE.md
Requires-Dist: kivy >=2.2.0
Requires-Dist: kivymd >=1.2.0
